prismix/core/iterative_programmer.py
prismix/main.py
prismix-0.1.0.dev0.dist-info/LICENSE
prismix-0.1.0.dev0.dist-info/METADATA
prismix-0.1.0.dev0.dist-info/WHEEL
prismix-0.1.0.dev0.dist-info/entry_points.txt
prismix-0.1.0.dev0.dist-info/RECORD
