Metadata-Version: 2.1
Name: prismix
Version: 0.1.0.dev0
Summary: An AI-powered code synthesis tool
Author: Tom Dörr
Author-email: tomdoerr96@gmail.com
Requires-Python: >=3.11,<3.12
Classifier: Programming Language :: Python :: 3
Classifier: Programming Language :: Python :: 3.11
Requires-Dist: dspy-ai (>=2.5.0,<3.0.0)
Requires-Dist: openai (>=1.0.0,<2.0.0)
Requires-Dist: pytest (>=8.3.3,<9.0.0)
Requires-Dist: pytest-asyncio (>=0.24.0,<0.25.0)
Requires-Dist: python-dotenv (>=1.0.0,<2.0.0)
